alu.v
/*对要执行的16种算术逻辑运算操作进行编码，编码为五位二进制数，从00001到10000
/是逻辑非操作，⊙是逻辑同或操作，⊕是逻辑异或操作。
*/
`define ADD     5'b00001        //F=A 加 B
`define ADDC    5'b00010        //F=A 加 B 加 Cin
`define SUB     5'b00011        //F=A 减 B
`define SUBC    5'b00100        //F=A 减 B 减 Cin
`define SUBF    5'b00101        //F=B 减 A
`define SUBFC   5'b00110        //F= B 减 A 减 Cin
`define ISA     5'b00111        //F=A
`define ISB     5'b01000        //F=B
`define NOTA    5'b01001        //F=/A
`define NOTB    5'b01010        //F=/B
`define OR      5'b01011        //F=A+B
`define AND     5'b01100        //F=AB
`define SAOR    5'b01101        //F=A⊙B
`define DIOR    5'b01110        //F=A⊕B
`define ANOT    5'b01111        //F=/(AB)
`define SETZ    5'b10000        //F=0
module alu (
    input  [31:0]   A   ,       //输入的32位运算数A
    input  [31:0]   B   ,       //输入的32位运算数B
    input           Cin ,       //进位
    input  [4 :0]   Card,       //5位运算操作码

    output [31:0]   F   ,       //32位运算结果
    output          Cout,       //结果进位
    output          Zero        //零标志
);
/*各操作的运算结果,与前面顺序一一对应*/
    wire [31:0]    add_result;
    wire [31:0]    addc_result;
    wire [31:0]    sub_result;
    wire [31:0]    subc_result;
    wire [31:0]    subf_result;
    wire [31:0]    subfc_result;
    wire [31:0]    isa_result;
    wire [31:0]    isb_result;
    wire [31:0]    nota_result;
    wire [31:0]    notb_result;
    wire [31:0]    or_result;
    wire [31:0]    and_result;
    wire [31:0]    saor_result;
    wire [31:0]    dior_result;
    wire [31:0]    anot_result;
    wire [31:0]    setz_result;
    wire cou1;
    wire cou2;
    wire cou3;
    wire cou4;
    wire cou5;
    wire cou6;
/*运算得出结果，与进位结果*/
    assign {cou1,add_result}=A+B;
    assign {cou2,addc_result}=A+B+Cin;
    assign {cou3,sub_result}=A-B;
    assign {cou4,subc_result}=A-B-Cin;
    assign {cou5,subf_result}=B-A;
    assign {cou6,subfc_result}=B-A-Cin;
    assign isa_result=A;
    assign isb_result=B;
    assign nota_result=~A;
    assign notb_result=~B;
    assign or_result=A|B;
    assign and_result=A&B;
    assign saor_result=~(A^B);
    assign dior_result=A^B;
    assign anot_result=~(A&B);
    assign setz_result=0;

/*当操作为对应操作时，对应结果不变，其他均为32b'0
最终结果为对应结果*/
    assign  F =     ({32{Card == `ADD}}  & add_result)  |
                    ({32{Card == `ADDC}}  & addc_result) |
                    ({32{Card == `SUB}}  & sub_result)  |
                    ({32{Card == `SUBC}}  & subc_result) |
                    ({32{Card == `SUBF}}  & subf_result) |
                    ({32{Card == `SUBFC}}  & subfc_result)|
                    ({32{Card == `ISA}}  & isa_result)  |
                    ({32{Card == `ISB}}  & isb_result)  |
                    ({32{Card == `NOTA}}  & nota_result) |
                    ({32{Card == `NOTB}}  & notb_result) |
                    ({32{Card == `OR}}  & or_result)   |
                    ({32{Card == `AND}}  & and_result)  |
                    ({32{Card == `SAOR}}  & saor_result) |
                    ({32{Card == `DIOR}} & dior_result) |
                    ({32{Card == `ANOT}}  & anot_result) |
                    ({32{Card == `SETZ}}  & setz_result);
/*对应操作Cout为对应进位，否则为0*/
    assign  Cout =  ({Card == `ADD}  & cou1) |
                    ({Card == `ADDC}  & cou2) |
                    ({Card == `SUB}   & cou3) |
                    ({Card == `SUBC}  & cou4) |
                    ({Card == `SUBF}  & cou5) |
                    ({Card == `SUBFC}  & cou6) ;
/*结果为0，Zero为1，否则为0*/
    assign  Zero =  ({Card == `ADD}  & add_result==0)  |
                    ({Card == `ADDC} & addc_result==0) |
                    ({Card == `SUB}  & sub_result==0)  |
                    ({Card == `SUBC} & subc_result==0) |
                    ({Card == `SUBF} & subf_result==0) |
                    ({Card == `SUBFC} & subfc_result==0)|
                    ({Card == `ISA}  & isa_result==0)  |
                    ({Card == `ISB}  & isb_result==0)  |
                    ({Card == `NOTA} & nota_result==0) |
                    ({Card == `NOTB}  & notb_result==0) |
                    ({Card == `OR}  & or_result==0)   |
                    ({Card == `AND}  & and_result==0)  |
                    ({Card == `SAOR}  & saor_result==0) |
                    ({Card == `DIOR} & dior_result==0) |
                    ({Card == `ANOT}  & anot_result==0) |
                    ({Card == `SETZ}  & setz_result==0);

endmodule

alu_ts.v
`timescale 1ns / 1ps
`include "alu.v"
////////////////////////////////////////////////////////////////////////////////
// Company: 
// Engineer:
//
// Create Date:   22:23:16 10/13/2021
// Design Name:   alu
// Module Name:   D:/Verilogprogram/alu/alu_ts.v
// Project Name:  alu
// Target Device:  
// Tool versions:  
// Description: 
//
// Verilog Test Fixture created by ISE for module: alu
//
// Dependencies:
// 
// Revision:
// Revision 0.01 - File Created
// Additional Comments:
// 
////////////////////////////////////////////////////////////////////////////////
// $monitor("a=%b, b=%b, y=%b", a, b, y);
//     $dumpfile("and2.vcd");  // 导出vcd文件
//     $dumpvars(0, and2_tb);  // 导出and2_tb模块中的所有变量
//     a = 0; b = 0; #10;
//     a = 0; b = 1; #10;
//     a = 1; b = 0; #10;
//     a = 1; b = 1; #10;
//     $finish;
module alu_ts;

	// Inputs
	reg [31:0] A;
	reg [31:0] B;
	reg Cin;
	reg [4:0] Card;

	// Outputs
	wire [31:0] F;
	wire Cout;
	wire Zero;

	// Instantiate the Unit Under Test (UUT)
	alu uut (
		.A(A), 
		.B(B), 
		.Cin(Cin), 
		.Card(Card), 
		.F(F), 
		.Cout(Cout), 
		.Zero(Zero)
	);

	initial begin
		$monitor("A=%b, B=%b, Cin=%b,Card=%b,F=%d,Cout=%d,Zero=%d", A, B, Cin,Card,F,Cout,Zero);
	    $dumpfile("alu.vcd");  // 导出vcd文件
		$dumpvars(0, alu_ts);  // 导出and2_tb模块中的所有变量
		// Initialize Inputs
		Card=5'b00001;
		A=(1<<<32)-1;
		B=1;
		Cin=1;
		// Wait 100 ns for global reset to finish  op2
		#10;
		Card=5'b00010;
		A=(1<<<32)-1;
		B=1;
		// Wait 100 ns for global reset to finish  op3
		#10;
		Card=5'b00011;
		A=(1<<<32)-1;
		B=1;
		// Wait 100 ns for global reset to finish  op4
		#10;
		Card=5'b00100;
		A=(1<<<32)-1;
		B=1;
		// Wait 100 ns for global reset to finish  op5
		#10;
		Card=5'b00101;	
		A=(1<<<32)-1;
		B=1;		
		// Wait 100 ns for global reset to finish  op6
		#10;
		Card=5'b00110;
		A=(1<<<32)-1;
		B=1;
		// Wait 100 ns for global reset to finish  op7
		#10;
		Card=5'b00111;
		A=(1<<<32)-1;
		B=1;	
		// Wait 100 ns for global reset to finish  op8
		#10;
		Card=5'b01000;
		A=(1<<<32)-1;
		B=1;	
		// Wait 100 ns for global reset to finish  op9
		#10;
		Card=5'b01001;
		A=(1<<<32)-1;
		B=1;	
		// Wait 100 ns for global reset to finish  op10
		#10;
		Card=5'b01010;
		A=(1<<<32)-1;
		B=1;		
		// Wait 100 ns for global reset to finish  op11
		#10;
		Card=5'b01011;
		A=(1<<<32)-1;
		B=1;		
		// Wait 100 ns for global reset to finish  op12
		#10;
		Card=5'b01100;
		A=(1<<<32)-1;
		B=1;	
		// Wait 100 ns for global reset to finish  op13
		#10;
		Card=5'b01101;
		A=(1<<<32)-1;
		B=1;	
		// Wait 100 ns for global reset to finish  op14
		#10;
		Card=5'b01110;
		A=(1<<<32)-1;
		B=1;		
		// Wait 100 ns for global reset to finish  op15
		#10;
		Card=5'b01111;
		A=(1<<<32)-1;
		B=1;	
		// Wait 100 ns for global reset to finish  op16
		#10;
		Card=5'b10000;
		A=(1<<<32)-1;
		B=1;	
		#10;	
		$finish;
    end
      
endmodule

alu.vcd
$date
	Thu Oct 21 18:46:18 2021
$end
$version
	Icarus Verilog
$end
$timescale
	1ps
$end
$scope module alu_ts $end
$var wire 1 ! Zero $end
$var wire 32 " F [31:0] $end
$var wire 1 # Cout $end
$var reg 32 $ A [31:0] $end
$var reg 32 % B [31:0] $end
$var reg 5 & Card [4:0] $end
$var reg 1 ' Cin $end
$scope module uut $end
$var wire 32 ( A [31:0] $end
$var wire 32 ) B [31:0] $end
$var wire 5 * Card [4:0] $end
$var wire 1 ' Cin $end
$var wire 1 # Cout $end
$var wire 32 + F [31:0] $end
$var wire 1 ! Zero $end
$var wire 32 , and_result [31:0] $end
$var wire 32 - anot_result [31:0] $end
$var wire 32 . dior_result [31:0] $end
$var wire 32 / isa_result [31:0] $end
$var wire 32 0 isb_result [31:0] $end
$var wire 32 1 nota_result [31:0] $end
$var wire 32 2 notb_result [31:0] $end
$var wire 32 3 or_result [31:0] $end
$var wire 32 4 saor_result [31:0] $end
$var wire 32 5 setz_result [31:0] $end
$var wire 32 6 subfc_result [31:0] $end
$var wire 32 7 subf_result [31:0] $end
$var wire 32 8 subc_result [31:0] $end
$var wire 32 9 sub_result [31:0] $end
$var wire 1 : cou6 $end
$var wire 1 ; cou5 $end
$var wire 1 < cou4 $end
$var wire 1 = cou3 $end
$var wire 1 > cou2 $end
$var wire 1 ? cou1 $end
$var wire 32 @ addc_result [31:0] $end
$var wire 32 A add_result [31:0] $end
$upscope $end
$upscope $end
$enddefinitions $end
#0
$dumpvars
b0 A
b1 @
1?
1>
0=
0<
1;
1:
b11111111111111111111111111111110 9
b11111111111111111111111111111101 8
b10 7
b1 6
b0 5
b1 4
b11111111111111111111111111111111 3
b11111111111111111111111111111110 2
b0 1
b1 0
b11111111111111111111111111111111 /
b11111111111111111111111111111110 .
b11111111111111111111111111111110 -
b1 ,
b0 +
b1 *
b1 )
b11111111111111111111111111111111 (
1'
b1 &
b1 %
b11111111111111111111111111111111 $
1#
b0 "
1!
$end
#10000
b1 "
b1 +
0!
b10 &
b10 *
#20000
b11111111111111111111111111111110 "
b11111111111111111111111111111110 +
0#
b11 &
b11 *
#30000
b11111111111111111111111111111101 "
b11111111111111111111111111111101 +
b100 &
b100 *
#40000
b10 "
b10 +
1#
b101 &
b101 *
#50000
b1 "
b1 +
b110 &
b110 *
#60000
b11111111111111111111111111111111 "
b11111111111111111111111111111111 +
0#
b111 &
b111 *
#70000
b1 "
b1 +
b1000 &
b1000 *
#80000
b0 "
b0 +
1!
b1001 &
b1001 *
#90000
0!
b11111111111111111111111111111110 "
b11111111111111111111111111111110 +
b1010 &
b1010 *
#100000
b11111111111111111111111111111111 "
b11111111111111111111111111111111 +
b1011 &
b1011 *
#110000
b1 "
b1 +
b1100 &
b1100 *
#120000
b1101 &
b1101 *
#130000
b11111111111111111111111111111110 "
b11111111111111111111111111111110 +
b1110 &
b1110 *
#140000
b1111 &
b1111 *
#150000
b0 "
b0 +
1!
b10000 &
b10000 *
